[
    {
        "instructor":"Sakib",
        "instructor_mail":"sakib1@gmail.com",
        "className":"Learning",
        "imageURL":"https://i.ibb.co/02cJZ3H/wicket-Keeping.jpg",
        "price":220,
        "seat":13,
        "subCategory":"Wicket Keeping",
        "stage":"Beginner",
        "classDetails":"Wicket Keeper",
        "status":"approve"
    },
    {
        "instructor":"Sakib",
        "instructor_mail":"sakib1@gmail.com",
        "className":"Learning",
        "imageURL":"https://i.ibb.co/fGHsymK/fast-Bowling.jpg",
        "price":299,
        "seat":14,
        "subCategory":"Fast Bowling",
        "stage":"Intermediate",
        "classDetails":"Fast Bowling Practice.",
        "status":"approve"
    },
    {
        "instructor":"Rakib",
        "instructor_mail":"rakib1@gmail.com",
        "className":"Learning",
        "imageURL":"https://i.ibb.co/c6Sj0Xz/spinbowling.jpg",
        "price":448,
        "seat":34,
        "subCategory":"Spin Bowling",
        "stage":"Beginner",
        "classDetails":"Spin Bowling Practice",
        "status":"approve"
    },
    {
        "instructor":"Rakib",
        "instructor_mail":"rakib1@gmail.com",
        "className":"Learning",
        "imageURL":"https://i.ibb.co/SXg3BPG/fielding.jpg",
        "price":220,
        "seat":9,
        "subCategory":"Fielding",
        "stage":"Beginner",
        "classDetails":"Fielding, Catch",
        "status":"approve"
    },
    {
        "instructor":"Edward Lyn",
        "instructor_mail":"edward@gmail.com",
        "className":"Learning",
        "imageURL":"https://i.ibb.co/MnV00VT/batting.jpg",
        "price":445,
        "seat":18,
        "subCategory":"Batting",
        "stage":"Beginner",
        "classDetails":"Batting Practice...",
        "status":"approve"
    },
    {
        "instructor":"Chris Brian",
        "instructor_mail":"brian@gmail.com",
        "className":"Learning",
        "imageURL":"https://i.ibb.co/YPwpQCX/football.jpg",
        "price":220,
        "seat":17,
        "subCategory":"Football",
        "stage":"Beginner",
        "classDetails":"Football, dribbling, shooting, passing etc.",
        "status":"approve"
    },
    {
        "instructor":"Jordan Leo",
        "instructor_mail":"jordan@gmail.com",
        "className":"Learning",
        "imageURL":"https://i.ibb.co/8mqgTzJ/tenis.jpg",
        "price":499,
        "seat":23,
        "subCategory":"Tennis",
        "stage":"Beginner",
        "classDetails":"Tennis",
        "status":"approve"
    },
    {
        "instructor":"Thomas Dimitri",
        "instructor_mail":"dimitri@gmail.com",
        "className":"Learning",
        "imageURL":"https://i.ibb.co/T1wRfBF/badminton.jpg",
        "price":449,
        "seat":23,
        "subCategory":"Badminton",
        "stage":"Beginner",
        "classDetails":"BasketBall",
        "status":"approve"
    },
    {
        "instructor":"Chris Steven",
        "instructor_mail":"steven@gmail.com",
        "className":"Learning",
        "imageURL":"https://i.ibb.co/pbtbTjR/basketball.jpg",
        "price":249,
        "seat":14,
        "subCategory":"Basketball",
        "stage":"Beginner",
        "classDetails":"Basketball",
        "status":"approve"
    },
    {
        "instructor":"Chris Steven",
        "instructor_mail":"steven@gmail.com",
        "className":"Learning",
        "imageURL":"https://i.ibb.co/bbG3MB5/pacebowlingjpg.jpg",
        "price":333,
        "seat":23,
        "subCategory":"Fast Bowling",
        "stage":"Beginner",
        "classDetails":"Pace Bowling",
        "status":"approve"
    },
    {
        "instructor":"Sakib",
        "instructor_mail":"sakib1@gmail.com",
        "className":"Learning",
        "imageURL":"https://i.ibb.co/d0B41mz/download-1.jpg",
        "price":444,
        "seat":28,
        "subCategory":"Badminton",
        "stage":"Beginner",
        "classDetails":"Basketball Pro",
        "status":"approve"
    },
    {
        "instructor":"Rakib",
        "instructor_mail":"rakib1@gmail.com",
        "className":"Learning",
        "imageURL":"https://i.ibb.co/XSPqFyY/featured.jpg",
        "price":999,
        "seat":15,
        "subCategory":"Wicket Keeping",
        "stage":"Beginner",
        "classDetails":"rffsdfesfgeg",
        "status":"pending"
    },
    {
        "instructor":"mama",
        "instructor_mail":"mama@gmail.com",
        "className":"3e4r3r",
        "imageURL":"https://i.ibb.co/gjKmj4s/download.png",
        "price":22,
        "seat":444,
        "subCategory":"Tennis",
        "stage":"Intermediate",
        "classDetails":"2332",
        "status":"pending"
    }
]